examples/multiplexers/two_to_one_mux.vhdl
entity two_to_one_mux is
    port (
        a, b, s : in bit;
        y : out bit
    );
end entity two_to_one_mux;

-- (a & ¬S) + (b & S)
architecture boolean of two_to_one_mux is
begin
    y <= (a and not s) or (b and s);
end boolean;

-- if s is 0, then y is a
-- if s is 1, then y is b
architecture algorithm of two_to_one_mux is
begin
    process (a, b, s) 
    begin
        if (s = '0') then
            y <= a;
        else 
            y <= b;
        end if;
    end process;
end algorithm;

-- behavioral
architecture behavioral of two_to_one_mux is
begin
    y <= a when (s = '1') else b;
end behavioral;

examples/multiplexers/two_to_one_mux_tb.vhdl
entity two_to_one_mux_tb is
end;

architecture tb of two_to_one_mux_tb is
    signal a, b, s : bit;
    signal y : bit;

begin

    ent_boolean : entity work.two_to_one_mux(boolean)
    port map (a, b, s, y);

    estimulo_checagem : process is

        type linha_tv is record
            a, b, s, y : bit;
        end record;

        type vetor_linha_tv is array (natural range <>) of linha_tv;

        constant tabela_verdade : vetor_linha_tv :=
        ( --  a    b    s    y
            ('0', '0', '0', '0'),  -- s is 0, then input a is selected, therefore y is 0.
            ('0', '0', '1', '0'),  -- s is 1, then input b is selected, therefore y is 0.
            ('0', '1', '0', '0'),  -- s is 0, then input a is selected, therefore y is 0.
            ('0', '1', '1', '1'),  -- s is 1, then input b is selected, therefore y is 1.
            ('1', '0', '0', '1'),  -- s is 0, then input a is selected, therefore y is 1.
            ('1', '0', '1', '0'),  -- s is 1, then input b is selected, therefore y is 0.
            ('1', '1', '0', '1'),  -- s is 0, then input a is selected, therefore y is 1.
            ('1', '1', '1', '1')   -- s is 1, then input b is selected, therefore y is 1.
        );

        begin 

            for i in tabela_verdade'range loop

                a <= tabela_verdade(i).a;
                b <= tabela_verdade(i).b;
                s <= tabela_verdade(i).s;

                wait for 1 ns;

                assert y = tabela_verdade(i).y report "Erro";
            
            end loop;

            report "Fim dos testes";

            wait;

    end process;

end tb;

examples/multiplexers/ondas.vcd
$date
  Sun Oct 11 13:34:33 2020
$end
$version
  GHDL v0
$end
$timescale
  1 fs
$end
$scope module standard $end
$upscope $end
$scope module two_to_one_mux_tb $end
$var reg 1 ! a $end
$var reg 1 " b $end
$var reg 1 # s $end
$var reg 1 $ y $end
$scope module ent_boolean $end
$var reg 1 % a $end
$var reg 1 & b $end
$var reg 1 ' s $end
$var reg 1 ( y $end
$upscope $end
$upscope $end
$enddefinitions $end
#0
0!
0"
0#
0$
0%
0&
0'
0(
#1000000
1#
1'
#2000000
1"
0#
1&
0'
#3000000
1#
1$
1'
1(
#4000000
1!
0"
0#
1%
0&
0'
#5000000
1#
0$
1'
0(
#6000000
1"
0#
1$
1&
0'
1(
#7000000
1#
1'
