examples/adders/single_bit_full_adder.vhdl
-- Ivan de Abreu Lima Junior
-- 7th October, 2020
-- 1 Bit Full Adder

entity single_bit_full_adder is
    port (
        a, b, cin : in bit;
        sum, cout : out bit
    );
end single_bit_full_adder;

architecture behavior of single_bit_full_adder is
begin 
    sum <= a xor b xor cin;
    cout <= (a and b) or (a and cin) or (b and cin);
end behavior;

examples/adders/single_bit_full_adder_tb.vhdl
entity single_bit_full_adder_tb is
end;

architecture logic of single_bit_full_adder_tb is
    signal a, b, cin, sum, cout : bit;
begin
    entidade : entity work.single_bit_full_adder(behavior)
    port map (a, b, cin, sum, cout);

    estimulo_checagem : process is
        type linha_tv is record
            a, b, cin, sum, cout : bit;
        end record;

        type vet_linha_tv is array (0 to 7) of linha_tv;
        constant tabela_verdade : vet_linha_tv :=
        --    a    b   cin  sum  out 
        (   ('0', '0', '0', '0', '0'),
            ('0', '0', '1', '1', '0'),
            ('0', '1', '0', '1', '0'),
            ('0', '1', '1', '0', '1'),
            ('1', '0', '0', '1', '0'),
            ('1', '0', '1', '0', '1'),
            ('1', '1', '0', '0', '1'),
            ('1', '1', '1', '1', '1')   );

    begin 

        for i in tabela_verdade'range loop
            a <= tabela_verdade(i).a;
            b <= tabela_verdade(i).b;
            cin <= tabela_verdade(i).cin;

            wait for 1 ns;

            assert sum = tabela_verdade(i).sum report "Erro";
            assert cout = tabela_verdade(i).cout report "Erro";

        end loop;

        report "Fim dos testes";

        wait;

    end process;

end logic;

examples/adders/ondas.vcd
$date
  Wed Oct  7 12:30:19 2020
$end
$version
  GHDL v0
$end
$timescale
  1 fs
$end
$scope module standard $end
$upscope $end
$scope module single_bit_full_adder_tb $end
$var reg 1 ! a $end
$var reg 1 " b $end
$var reg 1 # cin $end
$var reg 1 $ sum $end
$var reg 1 % cout $end
$scope module entidade $end
$var reg 1 & a $end
$var reg 1 ' b $end
$var reg 1 ( cin $end
$var reg 1 ) sum $end
$var reg 1 * cout $end
$upscope $end
$upscope $end
$enddefinitions $end
#0
0!
0"
0#
0$
0%
0&
0'
0(
0)
0*
#1000000
1#
1$
1(
1)
#2000000
1"
0#
1'
0(
#3000000
1#
0$
1%
1(
0)
1*
#4000000
1!
0"
0#
1$
0%
1&
0'
0(
1)
0*
#5000000
1#
0$
1%
1(
0)
1*
#6000000
1"
0#
1'
0(
#7000000
1#
1$
1(
1)
